lwh/__init__.py
lwh/main.py
lwh/report/__init__.py
lwh/report/report.py
lwh/utils.py
lwh-0.0.17.dist-info/entry_points.txt
lwh-0.0.17.dist-info/WHEEL
lwh-0.0.17.dist-info/METADATA
lwh-0.0.17.dist-info/RECORD
