Metadata-Version: 2.1
Name: lwh
Version: 0.0.17
Summary: 
Author: jeffthorne
Author-email: jthorne@u.washington.edu
Requires-Python: >=3.7,<4.0
Classifier: Programming Language :: Python :: 3
Classifier: Programming Language :: Python :: 3.7
Classifier: Programming Language :: Python :: 3.8
Classifier: Programming Language :: Python :: 3.9
Requires-Dist: Jinja2 (>=2.11.3,<3.0.0)
Requires-Dist: loguru (>=0.5.3,<0.6.0)
Requires-Dist: requests (>=2.25.1,<3.0.0)
Requires-Dist: typer[all] (>=0.3.2,<0.4.0)
